{
    "0": {
        "YEAR": 2017,
        "month": 10,
        "day": 30,
        "discount": 578.0,
        "discount_percentage": 32.13,
        "FLOORING": 0,
        "event_flag": 1,
        "ACCOUNT": "THD",
        "DC": "NTX",
        "MODEL": "LFCS22520D",
        "date": "2017-10-30",
        "ITEMDC": "LFCS22520DNTX",
        "MAP": 1799.0,
        "PMAP": 1221.0,
        "Inventory": 73.0,
        "PROMO": "BF",
        "BU": "REF",
        "SMSB_SUB_CATEGORY": "FRENCH DOOR",
        "WEEKNUM": 201744,
        "week": 44,
        "TARGET_QTY": 1400,
        "drop_in_week": 1,
        "QTY": 18,
        "event_groups_Low": 0,
        "event_groups_Mid": 0,
        "event_groups_Not Applicable": 0
    },
    "1": {
        "YEAR": 2017,
        "month": 11,
        "day": 6,
        "discount": 578.0,
        "discount_percentage": 32.13,
        "FLOORING": 0,
        "event_flag": 1,
        "ACCOUNT": "THD",
        "DC": "NTX",
        "MODEL": "LFCS22520D",
        "date": "2017-11-06",
        "ITEMDC": "LFCS22520DNTX",
        "MAP": 1799.0,
        "PMAP": 1221.0,
        "Inventory": 100.0,
        "PROMO": "BF",
        "BU": "REF",
        "SMSB_SUB_CATEGORY": "FRENCH DOOR",
        "WEEKNUM": 201745,
        "week": 45,
        "TARGET_QTY": 1400,
        "drop_in_week": 1,
        "QTY": 13,
        "event_groups_Low": 0,
        "event_groups_Mid": 0,
        "event_groups_Not Applicable": 0
    },
    "2": {
        "YEAR": 2017,
        "month": 11,
        "day": 13,
        "discount": 578.0,
        "discount_percentage": 32.13,
        "FLOORING": 0,
        "event_flag": 1,
        "ACCOUNT": "THD",
        "DC": "NTX",
        "MODEL": "LFCS22520D",
        "date": "2017-11-13",
        "ITEMDC": "LFCS22520DNTX",
        "MAP": 1799.0,
        "PMAP": 1221.0,
        "Inventory": 196.0,
        "PROMO": "BF",
        "BU": "REF",
        "SMSB_SUB_CATEGORY": "FRENCH DOOR",
        "WEEKNUM": 201746,
        "week": 46,
        "TARGET_QTY": 1400,
        "drop_in_week": 1,
        "QTY": 22,
        "event_groups_Low": 0,
        "event_groups_Mid": 0,
        "event_groups_Not Applicable": 0
    },
    "3": {
        "YEAR": 2017,
        "month": 11,
        "day": 20,
        "discount": 578.0,
        "discount_percentage": 32.13,
        "FLOORING": 0,
        "event_flag": 1,
        "ACCOUNT": "THD",
        "DC": "NTX",
        "MODEL": "LFCS22520D",
        "date": "2017-11-20",
        "ITEMDC": "LFCS22520DNTX",
        "MAP": 1799.0,
        "PMAP": 1221.0,
        "Inventory": 189.0,
        "PROMO": "BF",
        "BU": "REF",
        "SMSB_SUB_CATEGORY": "FRENCH DOOR",
        "WEEKNUM": 201747,
        "week": 47,
        "TARGET_QTY": 1400,
        "drop_in_week": 1,
        "QTY": 34,
        "event_groups_Low": 0,
        "event_groups_Mid": 0,
        "event_groups_Not Applicable": 0
    }
}